perfov/__init__.py
perfov/perfov.py
perfov-0.0.3.dist-info/LICENCE.md
perfov-0.0.3.dist-info/METADATA
perfov-0.0.3.dist-info/WHEEL
perfov-0.0.3.dist-info/top_level.txt
perfov-0.0.3.dist-info/RECORD
